ipa_notify/__init__.py
ipa_notify/__main__.py
ipa_notify/email_notifier.py
ipa_notify/ipa_adapter.py
ipa_notify/release.py
ipa_notify/templates/expired_password.j2
ipa_notify/templates/expiring_password.j2
ipa_notify/templates/locked_users.j2
ipa_notify-0.3.13.dist-info/LICENSE
ipa_notify-0.3.13.dist-info/METADATA
ipa_notify-0.3.13.dist-info/WHEEL
ipa_notify-0.3.13.dist-info/entry_points.txt
ipa_notify-0.3.13.dist-info/top_level.txt
ipa_notify-0.3.13.dist-info/RECORD
