Metadata-Version: 2.1
Name: ipa-notify
Version: 0.3.13
Summary: FreeIPA password expriation and locked user notifier
Home-page: https://github.com/cagdasbas/ipa-notify
Author: Cagdas Bas
Author-email: cagdasbs@gmail.com
License: UNKNOWN
Platform: UNKNOWN
Classifier: Development Status :: 5 - Production/Stable
Classifier: Intended Audience :: Developers
Classifier: Natural Language :: English
Classifier: License :: OSI Approved :: Apple Public Source License
Classifier: Programming Language :: Python
Classifier: Programming Language :: Python :: 3
Classifier: Programming Language :: Python :: 3.6
Classifier: Programming Language :: Python :: 3.8
Classifier: Programming Language :: Python :: 3.9
Requires-Python: >=3.6
Requires-Dist: python-freeipa (==1.0.6)
Requires-Dist: requests-kerberos (==0.12.0)
Requires-Dist: requests-gssapi (==1.2.3)
Requires-Dist: jinja2
